opac_htmlgen/__init__.py
opac_htmlgen/cli.py
opac_htmlgen/opac_htmlgen.py
opac_htmlgen-0.1.1.dist-info/DESCRIPTION.rst
opac_htmlgen-0.1.1.dist-info/METADATA
opac_htmlgen-0.1.1.dist-info/RECORD
opac_htmlgen-0.1.1.dist-info/WHEEL
opac_htmlgen-0.1.1.dist-info/entry_points.txt
opac_htmlgen-0.1.1.dist-info/metadata.json
opac_htmlgen-0.1.1.dist-info/top_level.txt
