Metadata-Version: 2.0
Name: opac-htmlgen
Version: 0.1.1
Summary: Small lib to generte HTML artcle page from (SciELO) SPS XML files
Home-page: https://github.com/jfunez/opac_htmlgen
Author: Juan Funez
Author-email: juan.funez@scielo.org
License: MIT license
Keywords: opac_htmlgen
Platform: UNKNOWN
Classifier: Development Status :: 2 - Pre-Alpha
Classifier: Intended Audience :: Developers
Classifier: License :: OSI Approved :: MIT License
Classifier: Natural Language :: English
Classifier: Programming Language :: Python :: 2
Classifier: Programming Language :: Python :: 2.6
Classifier: Programming Language :: Python :: 2.7
Classifier: Programming Language :: Python :: 3
Classifier: Programming Language :: Python :: 3.3
Classifier: Programming Language :: Python :: 3.4
Classifier: Programming Language :: Python :: 3.5
Requires-Dist: Click (>=6.0)
